odoo/addons/base_rule_visibility_restriction/README.rst
odoo/addons/base_rule_visibility_restriction/__init__.py
odoo/addons/base_rule_visibility_restriction/__manifest__.py
odoo/addons/base_rule_visibility_restriction/i18n/base_rule_visibility_restriction.pot
odoo/addons/base_rule_visibility_restriction/i18n/it.po
odoo/addons/base_rule_visibility_restriction/models/__init__.py
odoo/addons/base_rule_visibility_restriction/models/ir_rule.py
odoo/addons/base_rule_visibility_restriction/readme/CONTRIBUTORS.rst
odoo/addons/base_rule_visibility_restriction/readme/DESCRIPTION.rst
odoo/addons/base_rule_visibility_restriction/readme/USAGE.rst
odoo/addons/base_rule_visibility_restriction/static/description/icon.png
odoo/addons/base_rule_visibility_restriction/static/description/index.html
odoo/addons/base_rule_visibility_restriction/tests/__init__.py
odoo/addons/base_rule_visibility_restriction/tests/test_ir_rule.py
odoo/addons/base_rule_visibility_restriction/views/ir_rule_views.xml
odoo_addon_base_rule_visibility_restriction-16.0.1.0.0.2.dist-info/METADATA
odoo_addon_base_rule_visibility_restriction-16.0.1.0.0.2.dist-info/WHEEL
odoo_addon_base_rule_visibility_restriction-16.0.1.0.0.2.dist-info/top_level.txt
odoo_addon_base_rule_visibility_restriction-16.0.1.0.0.2.dist-info/RECORD
